stega_py/__init__.py
stega_py/module.py
cipher_Canvas-1.0.0.dist-info/METADATA
cipher_Canvas-1.0.0.dist-info/WHEEL
cipher_Canvas-1.0.0.dist-info/top_level.txt
cipher_Canvas-1.0.0.dist-info/RECORD
