Metadata-Version: 2.1
Name: cipher-Canvas
Version: 1.0.0
Summary: A package for embedding and extracting text within images using markers.
Author: Mani
License: MIT
Classifier: Programming Language :: Python :: 3
Classifier: License :: OSI Approved :: MIT License
Classifier: Operating System :: OS Independent
Requires-Dist: Pillow
